README.rst
gsqlite3.py
setup.cfg
setup.py
gsqlite3.egg-info/PKG-INFO
gsqlite3.egg-info/SOURCES.txt
gsqlite3.egg-info/dependency_links.txt
gsqlite3.egg-info/entry_points.txt
gsqlite3.egg-info/pbr.json
gsqlite3.egg-info/requires.txt
gsqlite3.egg-info/top_level.txt