Metadata-Version: 1.1
Name: gsqlite3
Version: 0.1.3
Summary: A wrapper for 'sqlite3' to make it play better with 'gevent'
Home-page: http://github.com/gilesbrown/gsqlite3
Author: Giles Brown
Author-email: giles_brown@hotmail.com
License: BSD
Download-URL: http://github.com/gilesbrown/gsqlite3/tarball/0.1.3
Platform: UNKNOWN
Classifier: Development Status :: 3 - Alpha
Classifier: Intended Audience :: Developers
Classifier: Natural Language :: English
Classifier: License :: OSI Approved :: BSD License
Classifier: Programming Language :: Python
Classifier: Programming Language :: Python :: 2.7
Classifier: Programming Language :: Python :: 3
Classifier: Programming Language :: Python :: 3.3
